Workbook

Sheet What Claude Costs You
A1: WHAT DOES IT COST FOR CLAUDE TO RUN THIS END-TO-END?
A2: Tundemy Kenya Marketing — Cost of Goods (Monthly)
A3: BLUE = Your input (change these) | B3: BLACK = Calculated | C3: GREEN = Good
A5: SECTION A — WHAT CLAUDE RUNS FOR FREE (Included in Your Subscription)
A6: Task | B6: Cadence | C6: Mode | D6: Who Does It | E6: Monthly Cost
A7: Research & build employer contact list (150 companies) | B7: Weekly | C7: Fully automated | D7: ✅ Done by Claude | E7: KSh 0
A8: Draft & personalise every email (3-touch per employer) | B8: Ongoing | C8: Fully automated | D8: ✅ Done by Claude | E8: KSh 0
A9: Write all Facebook posts (4/week) | B9: Weekly | C9: Fully automated | D9: ✅ Done by Claude | E9: KSh 0
A10: Write all WhatsApp broadcasts & messages | B10: Weekly | C10: Fully automated | D10: ✅ Done by Claude | E10: KSh 0
A11: Analyse campaign results & optimise | B11: Weekly | C11: Fully automated | D11: ✅ Done by Claude | E11: KSh 0
A12: A/B test messaging, rewrite underperformers | B12: Ongoing | C12: Fully automated | D12: ✅ Done by Claude | E12: KSh 0
A13: Build weekly performance reports | B13: Weekly | C13: Fully automated | D13: ✅ Done by Claude | E13: KSh 0
A14: Strategy adjustments based on data | B14: Monthly | C14: Fully automated | D14: ✅ Done by Claude | E14: KSh 0
A16: SECTION B — WHAT STILL NEEDS A HUMAN (You or a VA)
A17: Task | B17: Cadence | C17: Mode | D17: Who Does It | E17: Cost Note
A18: Press SEND on emails (or connect email tool) | B18: Daily | C18: Manual click | D18: You / VA | E18: 0 — or VA cost below
A19: Manage WhatsApp Business on your phone | B19: Daily | C19: Manual | D19: You / VA | E19: 0 — or VA cost below
A20: Approve Facebook ad spend in Meta Ads Manager | B20: Weekly | C20: Manual approval | D20: You | E20: 0 (5 min/week)
A21: Follow-up phone calls to warm employer leads | B21: Weekly | C21: Manual | D21: You / VA | E21: 0 — or VA cost below
A22: Post in Facebook Groups (community building) | B22: 3x/week | C22: Manual post | D22: You / VA | E22: 0 — or VA cost below
A24: SECTION C — RECOMMENDED MONTHLY TEAM COST
A25: Item | B25: Description | C25: Monthly (KSh) | D25: Monthly (USD ≈) | E25: Note
A26: Claude AI (Cowork) | B26: Full strategy, all content, all analysis, all optimisation | C26: — | D26: — | E26: Already paying — KSh 0 extra
A27: Marketing VA (part-time) | B27: Executes sends, manages WhatsApp, posts in groups, makes calls | C27: 35000 | D27: =C27/130 -> 269.23077 | E27: Recommended: 20 hrs/week
A28: Facebook Pixel setup (once) | B28: One-time developer fee to install pixel on tundemy.com | C28: 5000 | D28: =C28/130 -> 38.461538 | E28: One-time, not monthly
A29: TOTAL MONTHLY TEAM | C29: =C27 -> 35000 | D29: =C29/130 -> 269.23077

Sheet Assumptions
A1: MODEL ASSUMPTIONS — Change the blue cells to match your actual numbers
A2: BLUE = your inputs. All other sheets reference these cells. Update here first.
A3: REVENUE — COURSES
A4: Average course price (KSh) | B4: 5000 | C4: Update to your actual price
A5: Tundemy margin on each course (%) | B5: 0.92 | C5: Net after payment fees (~8% Pesapal)
A6: Avg courses per student per year | B6: 1.4 | C6: Some buy a 2nd course
A7: REVENUE — EMPLOYER SERVICES
A8: Talent profile unlock fee (KSh) | B8: 8000 | C8: Employer pays to see full contact + CV
A9: Job posting bundle (KSh) | B9: 15000 | C9: 5-job bundle posted on platform
A10: Employer unlock margin (%) | B10: 0.98 | C10: Near-pure margin — no delivery cost
A11: EMAIL CAMPAIGN
A12: Employers emailed per month | B12: 150 | C12: 50 per week
A13: Email open rate | B13: 0.35 | C13: Industry avg is 20%; AI skills = high interest
A14: Reply / positive response rate | B14: 0.08 | C14: 8% reply = 12 warm leads per month
A15: Replies that become job postings (%) | B15: 0.4 | C15: 4 of 10 warm leads post a job
A16: Job postings that buy an unlock (%) | B16: 0.3 | C16: 3 of 10 job posters buy unlock
A17: FACEBOOK — ORGANIC
A18: Page reach per post (people) | B18: 2000 | C18: Realistic for a new page with good content
A19: Click-through rate from organic (%) | B19: 0.02 | C19: 2% of reach clicks through to site
A20: Site visitor to lead conversion (%) | B20: 0.08 | C20: 8% submit email on landing page
A21: Lead to paid enrollment (%) | B21: 0.12 | C21: 12% of leads buy within 30 days
A22: FACEBOOK — PAID ADS
A23: Monthly ad budget (KSh) | B23: 90000 | C23: KSh 3,000/day as per strategy doc
A24: Cost per lead from ads (KSh) | B24: 250 | C24: Target — optimise toward this
A25: Lead to paid enrollment (paid ad) (%) | B25: 0.15 | C25: Slightly higher: more targeted
A26: WHATSAPP
A27: Broadcast list size (end of month 1) | B27: 500 | C27: 500 contacts by end of month 1
A28: Message open rate (%) | B28: 0.85 | C28: WhatsApp open rate is 85–98% in Kenya
A29: WA lead to enrollment (%) | B29: 0.07 | C29: 7% of broadcast list converts
A30: Referrals generated per month | B30: 30 | C30: From referral programme
A31: Referral conversion rate (%) | B31: 0.25 | C31: 25% of referred contacts enroll
A32: TOOL COSTS (Monthly KSh)
A33: Facebook ads budget | B33: 90000 | C33: See Paid Ads section above
A34: Apollo.io / email finding tool | B34: 8000 | C34: Find verified employer emails
A35: Canva Pro (design) | B35: 1700 | C35: All graphics and social assets
A36: Brevo CRM (email sequences) | B36: 2000 | C36: Email automation platform
A37: VA salary (part-time) | B37: 35000 | C37: Execution: sends, WhatsApp, calls
A38: Miscellaneous / buffer (10%) | B38: =SUM(B34:B37)*0.1 -> 4670 | C38: =SUM(B36:B40)*0.1 -> 4167

Sheet 90-Day ROI Model
A1: TUNDEMY — 90-DAY ROI MODEL (3 Scenarios)
A2: Metric | B2: Month 1 — Conservative | C2: Month 1 — Base Case | D2: Month 1 — Optimistic | E2: Month 2 — Base | F2: Month 3 — Base | G2: 3-Month Total — Base
A3: STUDENTS ACQUIRED (paying enrollments)
A4: From Facebook Paid Ads | B4: =INT(Assumptions!B23/Assumptions!B24*Assumptions!B25*0.7) -> 37 | C4: =INT(Assumptions!B23/Assumptions!B24*Assumptions!B25) -> 54 | D4: =INT(Assumptions!B23/Assumptions!B24*Assumptions!B25*1.4) -> 75 | E4: =INT(Assumptions!B23/Assumptions!B24*Assumptions!B25*1.2) -> 64 | F4: =INT(Assumptions!B23/Assumptions!B24*Assumptions!B25*1.5) -> 81
A5: From Facebook Organic | B5: =INT(4*Assumptions!B17*Assumptions!B18*Assumptions!B19*Assumptions!B20*0.6) -> 0 | C5: =INT(4*Assumptions!B17*Assumptions!B18*Assumptions!B19*Assumptions!B20) -> 0 | D5: =INT(4*Assumptions!B17*Assumptions!B18*Assumptions!B19*Assumptions!B20*1.8) -> 0 | E5: =INT(4*Assumptions!B17*Assumptions!B18*Assumptions!B19*Assumptions!B20*1.4) -> 0 | F5: =INT(4*Assumptions!B17*Assumptions!B18*Assumptions!B19*Assumptions!B20*2) -> 0
A6: From WhatsApp Broadcasts | B6: =INT(Assumptions!B26*Assumptions!B27*Assumptions!B28*0.6) -> 0 | C6: =INT(Assumptions!B26*Assumptions!B27*Assumptions!B28) -> 0 | D6: =INT(Assumptions!B26*Assumptions!B27*Assumptions!B28*1.5) -> 0 | E6: =INT(Assumptions!B26*Assumptions!B27*Assumptions!B28*1.3) -> 0 | F6: =INT(Assumptions!B26*Assumptions!B27*Assumptions!B28*1.7) -> 0
A7: From Email Referrals to Students | B7: =INT(Assumptions!B29*Assumptions!B30*0.5) -> 1 | C7: =INT(Assumptions!B29*Assumptions!B30) -> 2 | D7: =INT(Assumptions!B29*Assumptions!B30*2) -> 4 | E7: =INT(Assumptions!B29*Assumptions!B30*1.5) -> 3 | F7: =INT(Assumptions!B29*Assumptions!B30*2.5) -> 5
A8: TOTAL STUDENTS | B8: =SUM(B4:B7) -> 38 | C8: =SUM(C4:C7) -> 56 | D8: =SUM(D4:D7) -> 79 | E8: =SUM(E4:E7) -> 67 | F8: =SUM(F4:F7) -> 86 | G8: =E8+F8+C8 -> 209
A9: EMPLOYERS ENGAGED & REVENUE
A10: Warm employer replies (from email) | B10: =INT(Assumptions!B11*Assumptions!B12*0.6) -> 0 | C10: =INT(Assumptions!B11*Assumptions!B12) -> 0 | D10: =INT(Assumptions!B11*Assumptions!B12*1.8) -> 0 | E10: =INT(Assumptions!B11*Assumptions!B12*1.4) -> 0 | F10: =INT(Assumptions!B11*Assumptions!B12*2) -> 0
A11: Job postings secured | B11: =INT(B10*Assumptions!B13*0.6) -> 0 | C11: =INT(C10*Assumptions!B13) -> 0 | D11: =INT(D10*Assumptions!B13*1.5) -> 0 | E11: =INT(E10*Assumptions!B13) -> 0 | F11: =INT(F10*Assumptions!B13*1.3) -> 0
A12: Talent profile unlocks sold | B12: =INT(B11*Assumptions!B14*0.5) -> 0 | C12: =INT(C11*Assumptions!B14) -> 0 | D12: =INT(D11*Assumptions!B14*2) -> 0 | E12: =INT(E11*Assumptions!B14*1.5) -> 0 | F12: =INT(F11*Assumptions!B14*2) -> 0 | G12: =B12+E12+F12 -> 0
A13: REVENUE (KSh)
A14: Course revenue | B14: =B8*Assumptions!B4*Assumptions!B5 -> 174800 | C14: =C8*Assumptions!B4*Assumptions!B5 -> 257600 | D14: =D8*Assumptions!B4*Assumptions!B5 -> 363400 | E14: =E8*Assumptions!B4*Assumptions!B5 -> 308200 | F14: =F8*Assumptions!B4*Assumptions!B5 -> 395600 | G14: =B14+E14+F14 -> 878600
A15: Talent unlock revenue | B15: =B12*Assumptions!B7*Assumptions!B9 -> 0 | C15: =C12*Assumptions!B7*Assumptions!B9 -> 0 | D15: =D12*Assumptions!B7*Assumptions!B9 -> 0 | E15: =E12*Assumptions!B7*Assumptions!B9 -> 0 | F15: =F12*Assumptions!B7*Assumptions!B9 -> 0 | G15: =B15+E15+F15 -> 0
A16: Job posting bundle revenue | B16: =INT(B11*0.2)*Assumptions!B8 -> 0 | C16: =INT(C11*0.2)*Assumptions!B8 -> 0 | D16: =INT(D11*0.2)*Assumptions!B8 -> 0 | E16: =INT(E11*0.2)*Assumptions!B8 -> 0 | F16: =INT(F11*0.2)*Assumptions!B8 -> 0 | G16: =B16+E16+F16 -> 0
A17: TOTAL REVENUE | B17: =SUM(B14:B16) -> 174800 | C17: =SUM(C14:C16) -> 257600 | D17: =SUM(D14:D16) -> 363400 | E17: =SUM(E14:E16) -> 308200 | F17: =SUM(F14:F16) -> 395600 | G17: =SUM(G14:G16) -> 878600
A18: COSTS (KSh)
A19: Facebook Ads | B19: =Assumptions!B23 -> 90000 | C19: =Assumptions!B23 -> 90000 | D19: =Assumptions!B23 -> 90000 | E19: =Assumptions!B23*1.2 -> 108000 | F19: =Assumptions!B23*1.4 -> 126000 | G19: =B19+E19+F19 -> 324000
A20: Tools (Apollo, Canva, Brevo) | B20: =Assumptions!B34+Assumptions!B35+Assumptions!B36 -> 11700 | C20: =Assumptions!B34+Assumptions!B35+Assumptions!B36 -> 11700 | D20: =Assumptions!B34+Assumptions!B35+Assumptions!B36 -> 11700 | E20: =Assumptions!B34+Assumptions!B35+Assumptions!B36 -> 11700 | F20: =Assumptions!B34+Assumptions!B35+Assumptions!B36 -> 11700 | G20: =B20+E20+F20 -> 35100
A21: VA salary (execution) | B21: =Assumptions!B37 -> 35000 | C21: =Assumptions!B37 -> 35000 | D21: =Assumptions!B37 -> 35000 | E21: =Assumptions!B37 -> 35000 | F21: =Assumptions!B37 -> 35000 | G21: =B21+E21+F21 -> 105000
A22: Buffer / misc (10%) | B22: =(B19+B20+B21)*0.1 -> 13670 | C22: =(C19+C20+C21)*0.1 -> 13670 | D22: =(D19+D20+D21)*0.1 -> 13670 | E22: =(E19+E20+E21)*0.1 -> 15470 | F22: =(F19+F20+F21)*0.1 -> 17270 | G22: =B22+E22+F22 -> 46410
A23: TOTAL COSTS | B23: =SUM(B19:B22) -> 150370 | C23: =SUM(C19:C22) -> 150370 | D23: =SUM(D19:D22) -> 150370 | E23: =SUM(E19:E22) -> 170170 | F23: =SUM(F19:F22) -> 189970 | G23: =B23+E23+F23 -> 510510
A24: NET PROFIT & RETURN ON SPEND
A25: NET PROFIT (Revenue − Costs) | B25: =B17-B23 -> 24430 | C25: =C17-C23 -> 107230 | D25: =D17-D23 -> 213030 | E25: =E17-E23 -> 138030 | F25: =F17-F23 -> 205630 | G25: =G17-G23 -> 368090
A26: Return on Ad Spend (ROAS) | B26: =B17/B23 -> 1.1624659 | C26: =C17/C23 -> 1.7131077 | D26: =D17/D23 -> 2.4167055 | E26: =E17/E23 -> 1.81113 | F26: =F17/F23 -> 2.0824341 | G26: =G17/G23 -> 1.7210241
A27: ROI % | B27: =(B17-B23)/B23 -> 0.16246592 | C27: =(C17-C23)/C23 -> 0.71310767 | D27: =(D17-D23)/D23 -> 1.4167055 | E27: =(E17-E23)/E23 -> 0.81113005 | F27: =(F17-F23)/F23 -> 1.0824341 | G27: =(G17-G23)/G23 -> 0.72102407
A28: Cost to acquire 1 student (CAC) | B28: =IFERROR(B23/B8,0) -> 3957.1053 | C28: =IFERROR(C23/C8,0) -> 2685.1786 | D28: =IFERROR(D23/D8,0) -> 1903.4177 | E28: =IFERROR(E23/E8,0) -> 2539.8507 | F28: =IFERROR(F23/F8,0) -> 2208.9535 | G28: =IFERROR(G23/G8,0) -> 2442.6316
A29: Revenue per student (LTV proxy) | B29: =IFERROR(B17/B8,0) -> 4600 | C29: =IFERROR(C17/C8,0) -> 4600 | D29: =IFERROR(D17/D8,0) -> 4600 | E29: =IFERROR(E17/E8,0) -> 4600 | F29: =IFERROR(F17/F8,0) -> 4600 | G29: =IFERROR(G17/G8,0) -> 4203.8278

Sheet Break-Even & Payback
A1: BREAK-EVEN ANALYSIS & PAYBACK PERIOD
A2: BREAK-EVEN
A3: Monthly fixed costs (KSh) | B3: ='90-Day ROI Model'!C23 -> 150370
A4: Revenue per student (KSh) | B4: =Assumptions!B4*Assumptions!B5 -> 4600
A5: Students needed to break even | B5: =CEILING(B3/B4,1) -> 33
A6: Base-case students (Month 1) | B6: ='90-Day ROI Model'!C8 -> 56
A7: Break-even reached? | B7: =IF(B6>=B5,"YES — profitable from Month 1","NO — need more students") -> YES — profitable from Month 1
A9: PAYBACK PERIOD
A10: Cumulative cost Month 1 (KSh) | B10: ='90-Day ROI Model'!C23 -> 150370
A11: Cumulative revenue Month 1 (KSh) | B11: ='90-Day ROI Model'!C17 -> 257600
A12: Cumulative cost Month 2 (KSh) | B12: =B10+'90-Day ROI Model'!E23 -> 320540
A13: Cumulative revenue Month 2 (KSh) | B13: =B11+'90-Day ROI Model'!E17 -> 565800
A14: Cumulative cost Month 3 (KSh) | B14: =B12+'90-Day ROI Model'!F23 -> 510510
A15: Cumulative revenue Month 3 (KSh) | B15: =B13+'90-Day ROI Model'!F17 -> 961400
A16: NET cumulative (end Month 3) | B16: =B15-B14 -> 450890
A18: UNIT ECONOMICS
A19: Customer Acquisition Cost (CAC) | B19: ='90-Day ROI Model'!C28 -> 2685.1786
A20: Average Revenue Per User (ARPU) | B20: ='90-Day ROI Model'!C29 -> 4600
A21: LTV:CAC ratio (target > 3x) | B21: =IFERROR(B20/B19,0) -> 1.7131077
A22: Months to recover CAC | B22: =IFERROR(B19/B20,0) -> 0.58373447
